deric/__init__.py
deric/logs.py
deric/types/__init__.py
deric/types/enum_by_name.py
deric-0.2.3.dist-info/LICENSE
deric-0.2.3.dist-info/METADATA
deric-0.2.3.dist-info/WHEEL
deric-0.2.3.dist-info/RECORD
