Metadata-Version: 2.1
Name: deric
Version: 0.2.3
Summary: Declarative rich CLI
Home-page: https://github.com/cavenditti/deric
License: MIT
Author: Carlo Antonio Venditti
Author-email: c.a.venditti@pm.me
Requires-Python: >=3.10,<4.0
Classifier: License :: OSI Approved :: MIT License
Classifier: Programming Language :: Python :: 3
Classifier: Programming Language :: Python :: 3.10
Classifier: Programming Language :: Python :: 3.11
Classifier: Programming Language :: Python :: 3.12
Requires-Dist: pydantic (>=2.4.0,<3.0.0)
Requires-Dist: rich (>=13.6.0,<14.0.0)
Requires-Dist: tomlkit (>=0.11.6,<0.12.0)
Project-URL: Repository, https://github.com/cavenditti/deric
